scripts/etc/xrootd/xrdcp-tpc.sh
scripts/etc/xrootd/xrdsum.sh
xrdsum/__init__.py
xrdsum/_version.py
xrdsum/_version.pyi
xrdsum/cli.py
xrdsum/logger.py
xrdsum/py.typed
xrdsum/backends/__init__.py
xrdsum/backends/_base.py
xrdsum/backends/_cephfs.py
xrdsum/backends/_hdfs.py
xrdsum/backends/_http.py
xrdsum/backends/_posix.py
xrdsum/checksums/__init__.py
xrdsum/checksums/_base.py
xrdsum/checksums/_crc32c.py
xrdsum/checksums/adler32.py
xrdsum/storage_catalog/__init__.py
xrdsum/storage_catalog/_base.py
xrdsum/storage_catalog/cms.py
xrdsum-2025.2.1.dist-info/METADATA
xrdsum-2025.2.1.dist-info/WHEEL
xrdsum-2025.2.1.dist-info/entry_points.txt
xrdsum-2025.2.1.dist-info/licenses/LICENSE
xrdsum-2025.2.1.dist-info/RECORD
