Metadata-Version: 2.4
Name: xrdsum
Version: 2025.2.1
Summary: Package for retrieving and calculating checksums for XRootD
Project-URL: homepage, https://github.com/BristolComputing/xrdsum
Author-email: Luke Kreczko <kreczko@cern.ch>
Maintainer-email: The GridPP Collaboration <kreczko@cern.ch>
License: BSD 3-Clause License
License-File: LICENSE
Classifier: Development Status :: 4 - Beta
Classifier: Intended Audience :: Developers
Classifier: Intended Audience :: Science/Research
Classifier: License :: OSI Approved :: BSD License
Classifier: Operating System :: OS Independent
Classifier: Programming Language :: Python
Classifier: Programming Language :: Python :: 3
Classifier: Programming Language :: Python :: 3.9
Classifier: Programming Language :: Python :: 3.10
Classifier: Programming Language :: Python :: 3.11
Classifier: Topic :: Scientific/Engineering
Requires-Python: >=3.9
Requires-Dist: codetiming
Requires-Dist: crc32c
Requires-Dist: fasthep-logging>=0.1.1
Requires-Dist: requests
Requires-Dist: rich>=10.12.0
Requires-Dist: typer>=0.4.0
Requires-Dist: xattr>=0.10.1
Provides-Extra: dev
Requires-Dist: pytest>=6; extra == 'dev'
Provides-Extra: docs
Requires-Dist: myst-parser>=0.13; extra == 'docs'
Requires-Dist: sphinx-book-theme>=0.1.0; extra == 'docs'
Requires-Dist: sphinx-copybutton; extra == 'docs'
Requires-Dist: sphinx>=7.0; extra == 'docs'
Provides-Extra: hdfs
Requires-Dist: pyhdfs>=0.3.1; extra == 'hdfs'
Provides-Extra: test
Requires-Dist: pytest>=6; extra == 'test'
